docusign_exporter/__init__.py
docusign_exporter/docusign_exporter.py
docusign_exporter-1.0.3.dist-info/DESCRIPTION.rst
docusign_exporter-1.0.3.dist-info/METADATA
docusign_exporter-1.0.3.dist-info/RECORD
docusign_exporter-1.0.3.dist-info/WHEEL
docusign_exporter-1.0.3.dist-info/entry_points.txt
docusign_exporter-1.0.3.dist-info/metadata.json
docusign_exporter-1.0.3.dist-info/top_level.txt
